[ 
  {
  "id": "cumbum-sacwc-30th-annual-day-2026",
  "title": "கம்பம் ஸ்ரீ ஆதிசுஞ்சனகிரி மகளிர் கல்லூரி 30வது ஆண்டு விழா",
  "summary": "கம்பம் ஸ்ரீ ஆதிசுஞ்சனகிரி மகளிர் கல்லூரியில் 30வது ஆண்டு விழா சிறப்பாக நடைபெற்றது.",
  "image": "images/cumbum-sacwc.jpeg",
  "category": "மாவட்டம்",
  "date": "2026-02-27",
    "reporter": "கம்பம் விஜி",
    "place": "தேனி",
  "content": "கம்பம், ஸ்ரீ ஆதிசுஞ்சனகிரி மகளிர் கல்லூரியில்  30வது ஆண்டு விழா கல்லூரியின் நிறுவனச்செயலர் கம்பம் N.இராமகிருஷ்ணன் எம்.எல்.ஏ  தலைமையில் நடைபெற்றது. குத்துவிளக்கு ஏற்றப்பட்டு நிகழ்ச்சி தொடங்கியது.  கல்லூரி முதல்வர் டாக்டர்.ரேணுகா வரவேற்புரையாற்றி சிறப்பு விருந்தினர்களை அறிமுகப்படுத்தி அறிமுக உரையாற்றினார்.
 கல்லூரி இணைச்செயலர் வசந்தன் , வாழ்த்துரை வழங்கினார். இணைச்செயலர் தனது உரையில், மாணவிகள் சாதிக்கும் துறைகளில் இலக்கை அடைந்து பெற்றோருக்கும், ஆசிரியருக்கும், கல்லூரிக்கும், சமுதாயத்திற்கும் பெருமைசேர்க்க வேண்டும் என்று ஆலோசனை வழங்கினார். நிறுவனச்செயலர் கம்பம் N.இராமகிருஷ்ணன் எம்.எல்.ஏ  சிறப்பு விருந்தினர்களை கௌரவித்துப் பரிசு வழங்கினார். 
சிறப்பு விருந்தினர் இராயப்பன்பட்டி புனித ஆக்னஸ் பெண்கள் மேல்நிலைப்பள்ளி தலைமை ஆசிரியர் அருட்சகோதரி ஆ.மரிய நிர்மலா பேசுகையில், கல்விதான் பெண்களை உயர்த்தும் என்றும் பெண்கல்வியின் முக்கியத்துவம் குறித்தும் பெண்வாழ்க்கையில் லட்சியத்துடன் இலக்கை அடைந்து வாழ்வில் சோகம் இன்றி நல்ல நண்பர்களுடன்  மற்றவர்களுக்கு உதவி மகிழ்ச்சியுடன் வாழவேண்டும் என்றும் உரையாற்றினார். 
சின்னமனூர் K.V.A  பெண்கள் மேல்நிலைப்பள்ளி தலைமை ஆசிரியர் கிருஷ்ணலதா பேசுகையில் சிறந்த கல்வி மற்றும் நல்ல ஒழுக்கத்துடன் வாழ வேண்டும் என்றும் பெண்கள் கவனமாக இருக்க வேண்டும் செல்போன்களை சரியான முறையில் பயன்பபடுத்த வேண்டும் என்றும் கூறினார். காமயகவுண்டனடபட்டி கஸ்தூரிபாய் பெண்கள் மேல்நிலைப்பள்ளி தலைமை ஆசிரியர் கிருஷ்ணவேணி பேசுகையில், சமூக வலைதளங்களை சரியான முறையில் பயன்படுத்தி படிப்புடன் சிறந்த பழக்கவழக்கங்களை கடைபிடித்து தன்னம்பிக்கையுடன் வாழ்க்கையில் சாதனை செய்து ஆசிரியர்களுக்கும் பெற்றோர்களுக்கும் பெருமை சேர்க்க வேண்டும் என்று கூறினார்.
 மற்றும் சிறப்பு விருந்தினர் கூடலூர் என்எஸ்கேபி மேல்நிலைப்பள்ளி தலைமை ஆசிரியர் வெங்கட்குமார் பேசுகையில்,  கல்விதான் மாற்றத்தை உருவாக்கும் என்றும் சமுதாயத்தில் கௌரவத்தை உருவாக்குவதற்கு கல்விதான் துணை நிற்கும் என்றும் பேரறிஞர் அண்ணா, லெனின், அப்துல்கலாம் போன்ற அறிஞர்களை குறித்தும் பெண்கல்வியின் முக்கியத்துவம் குறித்தும் எடுத்துக்கூறினார். கல்லூரி நிறுவனர் அவர்கள் தனது தலைமை உரையில் புத்தக வாசிப்பின் அவசியம், செல்போன் தீமைகள் பற்றியும் நல்ல சிந்தனை நல்ல வார்த்தைகள் நல்ல பழக்கவழக்கங்கள் விதியை தீர்மானிக்கக்கூடியது என்றும் நெருக்கடியான சூழ்நிலையில் பதற்றமடையாமல் மௌனமாக இருந்து ஞானத்தை அடைய வேண்டும் என்றும் பெற்றோர்களுக்கும் ஆசிரியர்களுக்கும் கல்லூரிக்கும் பெருமை சேர்த்து வெற்றி பெற்று சமுதாயத்தில் மகிழ்ச்சியுடன் வாழ வேண்டும் என்று கூறினார். 
கல்லூரி ஒருங்கிணைப்பாளர் வைஷ்ணவி, கல்லூரி ஆலோசனைக்குழு உறுப்பினர்கள் கோபாலகிருஷ்ணன், சுப்பிரமணியன் ஆகியோர் கலந்து கொண்டனர். கல்வியில் முதன்மை பெற்ற  மாணவிகளுக்கும் சிறந்த செயல்பாடுகளில் முதன்மை பெற்ற மாணவிகளுக்கும் பரிசுகள் வழங்கப்பட்டன.கல்லூரிப் பேராசிரியர்கள், அலுவலகப்பணியாளர்கள், சமையலர், துப்புரவுப் பணியாளர்கள், கல்லூரிப் பேருந்து ஓட்டுநர் அனைவருக்கும் பரிசுகள் வழங்கப்பட்டன. கல்லூரிப் பேரவை மாணவிகளுக்கு  பரிசுகள் வழங்கப்பட்டன. இதனைத்தொடர்ந்து மாணவிகளின் கலைநிகழ்ச்சிகள் நடைபெற்றன. கல்லூரிப் பேரவை உறுப்பினர் டாக்டர்.சு.தமிழ்ச்செல்வி நன்றியுரை வழங்கினார். இவ்விழாவில் கல்லூரிப் பேராசிரியர்கள், மாணவிகள் மற்றும் அலுவலர்கள் அனைவரும் கலந்து கொண்டு நிகழ்வினை சிறப்பித்தனர்
"
},
   {
    "id": "periyartiger-2026",
    "title": "பெரியார் புலிகள் கணக்கெடுப்பு 2026",
    "summary": "பெரியார் புலிகள் காப்பகத்தில் மூன்றாம் கட்ட கணக்கெடுப்பு தொடங்கியது.",
    "image": "images/periyartiger.jpg",
    "category": "மாவட்டம்",
    "date": "2026-02-26",
    "content": "தேசிய அளவிலான புலிகள் கணக்கெடுப்பின் ஒரு பகுதியாக பெரியார் புலிகள் காப்பகத்தில் மூன்றாம் கட்ட கேமரா டிராப்பிங் பணிகள் தொடங்கியுள்ளன. மொத்தம் 940 கேமராக்கள் பொருத்தப்பட்டுள்ளன. இந்த கணக்கெடுப்பு மார்ச் 27 வரை நடைபெறும்."
  },
 {
  "id": "bodimettu-lory-traffic",
  "title": "போடி மெட்டு மலைச்சாலையில் லாரி பழுதால் 3 மணி நேரம் போக்குவரத்து பாதிப்பு",
  "summary": "போடிமெட்டு மலைச்சாலையில் பழுதாகி நின்ற லாரியால் மூன்று மணி நேரம் போக்குவரத்து பாதிப்பு.",
  "image": "/puthiyaparvai-web/images/news/bodimettu-lory.jpeg",
  "link": "/puthiyaparvai-web/news/bodimettu-lory-traffic.html",
  "category": "maavattam",
  "breaking": false,
  "date": "2026-02-26"
},
 {
  "title": "கூடலூரில் குப்பைகிடங்கை நிரந்தர இடமாற்றம் செய்யக்கோரி பொதுமக்கள் போராட்டம்",
  "summary": "பெத்துக்குளம் பகுதியில் குப்பைகிடங்கை நிரந்தரமாக மாற்றக் கோரி பொதுமக்கள் தொடர் போராட்டம்.",
  "image": "/puthiyaparvai-web/images/news/gdr-kuppai-people.jpeg",
  "link": "/puthiyaparvai-web/news/gudalur-kuppai-porattam.html",
  "category": "maavattam",
  "breaking": false,
  "date": "2026-02-23"
},
 {
  "title": "ஏ.ஐ., தொழில்நுட்பத்தால் மகள் திருமணத்திற்கு வந்த மறைந்த தந்தை",
  "summary": "ஏ.ஐ., தொழில்நுட்பம் மூலம் மறைந்த தந்தை மகள் திருமணத்தில் கலந்து கொண்ட நிகழ்வு.",
  "image": "https://newsdonkey24-stack.github.io/puthiyaparvai-web/images/news/cumbum-ai-tec.jpeg",
  "link": "https://newsdonkey24-stack.github.io/puthiyaparvai-web/news/ai-wedding-kambam.html",
  "category": "district",
  "breaking": false,
  "date": "2026-02-23"
},
 {
  "title": "த.வெ.க வார்டு நிர்வாகிகள் கூட்டம்",
  "summary": "உத்தமபாளையத்தில் நடைபெற்ற தமிழக வெற்றி கழக வார்டு நிர்வாகிகள் கூட்டம்",
  "image": "/puthiyaparvai-web/images/news/upm-tvk-1.jpeg",
  "link": "/puthiyaparvai-web/news/tvk-ward-meeting-uthamapalayam.html",
  "category": "arasiyal",
  "breaking": false,
  "date": "2026-02-22"
},
 {
  "title": "போக்சோ பாலியல் வன்முறை சட்டங்கள் விழிப்புணர்வு முகாம்",
  "summary": "மெய்வழி மக்கள் இயக்கம் சார்பில் போக்சோ சட்ட விழிப்புணர்வு முகாம் நடத்தப்பட்டது",
  "image": "/puthiyaparvai-web/images/news/pocso-varusai-makkal.jpeg",
  "link": "/puthiyaparvai-web/news/pocso-varusai-awareness.html",
  "category": "maavattam",
  "breaking": false,
  "date": "2026-02-21"
},
 {
  "title": "போக்சோ பாலியல் வன்முறை சட்டங்கள் பற்றிய விழிப்புணர்வு முகாம்",
  "summary": "மெய்வழி மக்கள் இயக்கம் சார்பில் போக்சோ பாலியல் வன்முறை பற்றிய விழிப்புணர்வு முகாம் கம்பத்தில் நடைபெற்றது.",
  "image": "https://newsdonkey24-stack.github.io/puthiyaparvai-web/images/news/varusai-makkal.jpeg",
  "link": "https://newsdonkey24-stack.github.io/puthiyaparvai-web/news/varusai-makkal-pocso-awareness.html",
  "category": "district",
  "breaking": false,
  "date": "2026-02-21"
},
 {
  "title": "தமிழ்நாடு அறிவியல் இயக்கம் சார்பில் 27 ஆவது கம்பம் சந்திப்பு",
  "summary": "தமிழ்நாடு அறிவியல் இயக்கம் சார்பில் கம்பத்தில் நடைபெற்ற 27வது சந்திப்பு நிகழ்வு.",
  "image": "/puthiyaparvai-web/images/news/science-meet.jpeg",
  "link": "/puthiyaparvai-web/news/tamilnadu-science-meet-27.html",
  "category": "maavattam",
  "breaking": false,
  "date": "2026-02-21"
},
 {
  "title": "தமிழ்நாடு அறிவியல் இயக்கம் சார்பில் 27 ஆவது கம்பம் சந்திப்பு",
  "summary": "தமிழ்நாடு அறிவியல் இயக்கம் சார்பில் கம்பம் சந்திப்பு 27வது நிகழ்வு இன்று கம்பத்தில் நடைபெற்றது.",
  "image": "/puthiyaparvai-web/images/news/cumbum-science.jpeg",
  "link": "/puthiyaparvai-web/cumbum-science-meet-27.html",
  "category": "maavattam",
  "breaking": false,
  "date": "2026-02-21"
},
 {
  "title": "கூடலூர் பள்ளி விளையாட்டு விழா",
  "summary": "கூடலூர் மழலையர் மெட்ரிக் பள்ளியில் நடைபெற்ற விளையாட்டு விழா குறித்து செய்தி.",
  "image": "/puthiyaparvai-web/images/news/gdr-school-sports1.jpeg",
  "link": "/puthiyaparvai-web/news/gudalur-school-sports.html",
  "category": "vilaiyattu",
  "breaking": false,
  "date": "2026-02-21"
},
 {
  "title": "உலக தாய்மொழி தினத்தை முன்னிட்டு \"துணிந்து நில்\" அறக்கட்டளை சார்பில் குருதிக்கொடை முகாம்",
  "summary": "உலக தாய்மொழி தினத்தை முன்னிட்டு கம்பத்தில் நடைபெற்ற துணிந்து நில் அறக்கட்டளை சார்பிலான குருதிக்கொடை முகாம் பற்றிய முழு விவரம்.",
  "image": "/puthiyaparvai-web/images/news/cumbum-blood-donate.jpeg",
  "link": "/puthiyaparvai-web/news/cumbum-blood-donation-mother-language-day.html",
  "category": "maavattam",
  "breaking": false,
  "date": "2026-02-21"
},
 {
  "title": "மூணாறின் 'தாஜ்மஹால்': ஒரு காதல் காவியமும்... கடல் விழுங்கிய மர்மமும்",
  "summary": "மூணாறின் CSI தேவாலயத்தின் காதல் கதை மற்றும் கடல் மர்மம் பற்றிய முழு கட்டுரை.",
  "image": "/puthiyaparvai-web/images/news/munnar-1.jpeg",
  "link": "/puthiyaparvai-web/news/munnar-tajmahal-mystery.html",
  "category": "sutrula",
  "breaking": true,
  "date": "2026-02-20"
},
 {
  "title": "கம்பம் வாவேர் பள்ளியில் ரமலான் நோன்பு திறப்பு நிகழ்ச்சி",
  "summary": "கம்பம் நகரில் உள்ள 300 ஆண்டுகள் பழமையான வாவேர் பள்ளிவாசலில் புனித ரமலானை முன்னிட்டு முதல் நோன்பு திறப்பு நிகழ்ச்சி சிறப்பாக நடைபெற்றது.",
  "image": "/puthiyaparvai-web/images/news/cumbum-vaver-ramzan.jpeg",
  "link": "/puthiyaparvai-web/news/cumbum-vaver-ramzan.html",
  "category": "maavattam",
  "breaking": true,
  "date": "2026-02-19"
},
 {
  "title": "தேனி & இடுக்கி மாவட்ட எல்லையை அளவீடு செய்ய வேண்டும் – பெரியாறு வைகை பாசன விவசாயிகள் சங்கம் கோரிக்கை",
  "summary": "தேனி–இடுக்கி மாவட்ட எல்லையை போர்க்கால அடிப்படையில் அளவீடு செய்து ஆக்கிரமிப்புகளை தடுக்க தமிழக அரசு நடவடிக்கை எடுக்க வேண்டும் என பெரியாறு வைகை பாசன விவசாயிகள் சங்கம் கோரிக்கை விடுத்துள்ளது.",
  "image": "/puthiyaparvai-web/images/news/anwer-vivasayi.jpeg",
  "link": "/puthiyaparvai-web/news/theni-idukki-border-survey.html",
  "category": "maavattam",
  "breaking": false,
  "date": "2026-02-19"
},
 {
  "title": "மனிதநேய மக்கள் கட்சியின் 18-ம் ஆண்டு துவக்க தினம்",
  "summary": "கம்பம் அரசு மருத்துவமனையில் 150 பேருக்கு உணவு பொருட்கள், 50 குழந்தைகளுக்கு உடைகள் வழங்கிய மனிதநேய மக்கள் கட்சி.",
  "image": "/puthiyaparvai-web/images/news/cumbum-mmk.jpeg",
  "link": "/puthiyaparvai-web/news/cumbum-mmk-18th-anniversary.html",
  "category": "arasiyal",
  "breaking": false,
  "date": "2026-02-19"
},
 {
  "title": "கேரளாவுக்கு கடத்த முயன்ற 40 கிலோ கஞ்சா பறிமுதல் – ரூ.1.20 லட்சம் ரொக்கம் கைப்பற்றப்பட்டது; பெண் உட்பட 3 பேர் கைது",
  "summary": "லோயர் கேம்பில் கேரளாவுக்கு கடத்த முயன்ற 40 கிலோ கஞ்சா, ரூ.1.20 லட்சம் ரொக்கம், செல்போன்கள் மற்றும் சொகுசு கார் பறிமுதல். பெண் உட்பட 3 பேர் கைது.",
  "image": "/puthiyaparvai-web/images/news/lower-ganja.jpeg",
  "link": "/puthiyaparvai-web/news/lower-ganja-seizure.html",
  "category": "kutram",
  "breaking": true,
  "date": "2026-02-18"
},
 {
  "title": "திமுக அரசை கண்டித்து, கம்பம் ஒன்றிய அதிமுக சார்பில் கண்டன ஆர்ப்பாட்டம்",
  "summary": "125 நாள் வேலை உறுதித் திட்டத்தை  சீர்குலைக்க முயல்வதாக மு க ஸ்டாலின் தலைமையிலான திமுக அரசை கண்டித்து கம்பம் ஒன்றிய அதிமுக சார்பில் கன்றா ஆர்ப்பாட்டம் நடைபெற்றது.",
  "image": "/puthiyaparvai-web/images/news/cumbum-admk.jpeg",
  "link": "/puthiyaparvai-web/news/cumbum-admk-protest.html",
  "category": "arasiyal",
  "breaking": false,
 "date": "2026-02-18"
},
 {
  "title": "நாடு தழுவிய ேவலை நிறுத்தம்: தமிழக எல்லையில் இயல்பு வாழ்க்கை பாதிப்பு",
  "summary": "நாடு முழுவதும் நடைபெற்ற வேலை நிறுத்த போராட்டத்தால் தமிழக–கேரள எல்லைப் பகுதிகளில் போக்குவரத்து முடங்கியது. ஆயிரக்கணக்கான தோட்டத் தொழிலாளர்கள் பாதிக்கப்பட்டனர்.",
  "image": "/puthiyaparvai-web/images/news/cumbum-strike.jpeg",
  "link": "/puthiyaparvai-web/news/cumbum-strike-kerala-border.html",
  "category": "arasiyal",
  "breaking": false,
 "date": "2026-02-17"
},
 {
  "title": " கம்பத்தில் பல ஆண்டுகளாக ஆக்கிரமித்து கட்டப்பட்டிருந்த வீடுகள் இடித்து அகற்றம்",
  "summary": " கம்பத்தில் பல ஆண்டுகளாக ஆக்கிரமித்து கட்டப்பட்டிருந்த வீடுகள் முழுவதுமாக இடித்து அகற்றம் செய்யப்பட்டது",
  "image": "/puthiyaparvai-web/images/news/image-name.jpeg",
  "link": "/puthiyaparvai-web/news/file-name.html",
  "category": "maavattam",
  "breaking": false,
 "date": "2026-02-17"
},
 {
  "title": "மனிதநேய மக்கள் கட்சியின் 18-ம் ஆண்டு விழா!",
  "summary": "தேனி உத்தமபாளையத்தில் மனிதநேய மக்கள் கட்சியின் 18-ம் ஆண்டு விழாவை முன்னிட்டு கொடியேற்றி, நலத்திட்ட உதவிகள் மற்றும் முதியோர் இல்லத்தில் உணவு வழங்கப்பட்டது.",
  "image": "/puthiyaparvai-web/images/news/sdpi-cumbum.jpeg",
  "link": "/puthiyaparvai-web/news/sdpi-18th-anniversary-uthamapalayam.html",
  "category": "arasiyal",
  "breaking": false,
 "date": "2026-02-16"
},
 {
  "title": "சட்டமன்றத் தேர்தலில் எந்த கட்சியோடு கூட்டணி அமைத்தாலும் கம்பம் தொகுதியில் போட்டியிடுவேன் - ஜெகநாத் மிஸ்ரா",
  "summary": "எந்த கட்சியோடு கூட்டணி அமைத்தாலும் கம்பம் தொகுதியில் போட்டியிடுவேன் என ஜெகநாத் மிஸ்ரா தெரிவித்தார்.",
  "image": "/puthiyaparvai-web/images/news/misra-news-cumbum.jpeg",
  "link": "/puthiyaparvai-web/news/misra-election-cumbum.html",
  "breaking": false,
  "category": "arasiyal",
  "date": "2026-02-15"
},
 {
  "title": "லோயர் - குமுளி மலைச்சாலையில் பிளாஸ்டிக் கழிவுகள் அகற்றம்",
  "summary": "லோயர் - குமுளி மலைச்சாலையில் வனத்துறையினர் மற்றும் பள்ளி மாணவர்கள் இணைந்து பிளாஸ்டிக் கழிவுகளை அகற்றினர்.",
  "image": "/puthiyaparvai-web/images/news/gdr-forest.jpeg",
  "link": "/puthiyaparvai-web/news/lower-kumuli-plastic-cleaning.html",
  "breaking": false,
    "category": "maavattam",
  "date": "2026-02-14"
},
 {
    "title": "தேசிய தொழுநோய் விழிப்புணர்வு முகாம்",
    "summary": "கம்பத்தில் நடைபெற்ற தேசிய தொழுநோய் விழிப்புணர்வு முகாம் பொதுமக்களிடையே விழிப்புணர்வை ஏற்படுத்தியது.",
    "image": "/puthiyaparvai-web/images/news/leprosy-camp-kambam.jpeg",
    "link": "/puthiyaparvai-web/news/national-leprosy-awareness-camp.html",
    "breaking": false,
    "date": "2026-02-14"
},
  {
    "title": "பெரியாறு அணை வெடிகுண்டு மிரட்டல்",
    "summary": "பெரியாறு அணைக்கு வந்த மிரட்டலை தொடர்ந்து போலீசார் தீவிர விசாரணை மேற்கொண்டு வருகின்றனர்.",
    "image": "/puthiyaparvai-web/images/news/idukki-police.jpeg",
    "link": "/puthiyaparvai-web/news/periyar-idukki-bomb-threat.html",
    "breaking": false,
   "date": "2026-02-13"
},
 {
  "title": "டெஸ்ட் செய்தி - Auto System வேலை செய்கிறது",
  "summary": "இந்த செய்தி auto homepage system மூலம் தானாக வந்துள்ளது.",
  "image": "/puthiyaparvai-web/images/news/test.jpg",
  "link": "/puthiyaparvai-web/news/test-news.html",
  "breaking": false,
  "date": "2026-02-13"
},
 {
  "title": "கம்பத்தில் புதிய ஆம்னி பஸ் நிலையம், புதிய வணிக வளாகம் திறப்பு",
  "summary": "கம்பத்தில் ரூ.2.65 கோடி மதிப்பில் ஆம்னி பஸ் நிலையமும், ரூ.1.78 கோடி மதிப்பில் வணிக வளாகமும் முதல்வர் மு.க.ஸ்டாலின் காணொலி மூலம் திறந்து வைத்தார்.",
  "image": "/puthiyaparvai-web/image/kambam-bus-stand.jpeg",
  "link": "/puthiyaparvai-web/news/kambam-new-bus-stand.html",
  "breaking": false,
 "date": "2026-02-13"
},
 {
  "title": "கம்பம் அரசு மருத்துவமனையில் அவசர பேறுகால சிகிச்சை மையம் திறப்பு விழா",
  "summary": "கம்பம் அரசு மருத்துவமனையில் ரூ.10 கோடி செலவில் கட்டப்பட்ட ஒருங்கிணைந்த அவசர பேறுகால மற்றும் பச்சிளங்குழந்தைகளுக்கான தீவிர சிகிச்சை மையம் திறப்பு.",
  "image": "/puthiyaparvai-web/images/news/kambam-hospital-opening.jpeg",
  "link": "/puthiyaparvai-web/news/kambam-hospital-opening.html",
  "breaking": false,
   "date": "2026-02-12"
},
 {
  "title": "கம்பம் ஸ்ரீ கம்பராய பெருமாள் கோவிலில் மூத்த தம்பதியருக்கு சிறப்பு செய்யும் நிகழ்ச்சி: கம்பம் எம் எல் ஏ பங்கேற்பு",
  "summary": "கம்பத்தில் உள்ள கம்பராய பெருமாள் கோவிலில் மூத்த தம்பதியர்களுக்கு சிறப்பு செய்யும் நிகழ்ச்சியில் கம்பம் எம் எல் ஏ ராமகிருஷ்ணன் பங்கேற்றார்.",
  "image": "/puthiyaparvai-web/images/news/cumbum-kovil-mla.jpeg",
  "link": "/puthiyaparvai-web/news/cumbum-kovil-mla-special-couples.html",
  "category": "arasiyal",
  "breaking": false,
 "date": "2026-02-12"
}
]
